LeetcodeCookbook/README.md
LeetcodeCookbook/__init__.py
LeetcodeCookbook/__main__.py
LeetcodeCookbook/file.epub
LeetcodeCookbook/index.html
LeetcodeCookbook/css/__init__.py
LeetcodeCookbook/css/annotations.css
LeetcodeCookbook/css/main.css
LeetcodeCookbook/css/normalize.css
LeetcodeCookbook/css/popup.css
LeetcodeCookbook/font/__init__.py
LeetcodeCookbook/font/fontello.eot
LeetcodeCookbook/font/fontello.svg
LeetcodeCookbook/font/fontello.ttf
LeetcodeCookbook/font/fontello.woff
LeetcodeCookbook/img/__init__.py
LeetcodeCookbook/img/annotator-glyph-sprite.png
LeetcodeCookbook/img/annotator-icon-sprite.png
LeetcodeCookbook/img/apple-touch-icon.png
LeetcodeCookbook/img/cancelfullscreen.png
LeetcodeCookbook/img/close.png
LeetcodeCookbook/img/fullscreen.png
LeetcodeCookbook/img/loader.gif
LeetcodeCookbook/img/menu-icon.png
LeetcodeCookbook/img/save.png
LeetcodeCookbook/img/saved.png
LeetcodeCookbook/img/settings-s.png
LeetcodeCookbook/img/settings.png
LeetcodeCookbook/img/star.png
LeetcodeCookbook/js/__init__.py
LeetcodeCookbook/js/epub.js
LeetcodeCookbook/js/epub.min.js
LeetcodeCookbook/js/epub.min.map
LeetcodeCookbook/js/hooks.min.js
LeetcodeCookbook/js/hooks.min.map
LeetcodeCookbook/js/reader.js
LeetcodeCookbook/js/reader.js.map
LeetcodeCookbook/js/reader.min.js
LeetcodeCookbook/js/reader.min.map
LeetcodeCookbook/js/hooks/__init__.py
LeetcodeCookbook/js/hooks/extensions/__init__.py
LeetcodeCookbook/js/hooks/extensions/highlight.js
LeetcodeCookbook/js/libs/__init__.py
LeetcodeCookbook/js/libs/jquery.min.js
LeetcodeCookbook/js/libs/localforage.min.js
LeetcodeCookbook/js/libs/screenfull.js
LeetcodeCookbook/js/libs/screenfull.min.js
LeetcodeCookbook/js/libs/zip.min.js
LeetcodeCookbook/js/plugins/__init__.py
LeetcodeCookbook/js/plugins/hypothesis.js
LeetcodeCookbook/js/plugins/search.js
leetcode_cookbook-2024.3.6.0.dist-info/METADATA
leetcode_cookbook-2024.3.6.0.dist-info/WHEEL
leetcode_cookbook-2024.3.6.0.dist-info/entry_points.txt
leetcode_cookbook-2024.3.6.0.dist-info/top_level.txt
leetcode_cookbook-2024.3.6.0.dist-info/RECORD
